setup.py
./__init__.py
./account.py
./account.xml
./analytic_account.py
./analytic_account_coop_ar.xml
./balance_social.odt
./header_A4.odt
./meeting.py
./meeting.xml
./partner.py
./partner.xml
./partnermeeting.py
./partners_coop_ar.py
./recibo.odt
./recibo.py
./recibo.xml
./sanction.py
./sanction.xml
./setup.py
./tryton.cfg
./vacation.py
./vacation.xml
./locale/es_AR.po
./view/analytic_account_nota_form.xml
./view/analytic_account_nota_tree.xml
./view/fiscalyear_form.xml
./view/meeting_form.xml
./view/meeting_partners_tree.xml
./view/meeting_tree.xml
./view/partner_form.xml
./view/partner_tree.xml
./view/print_balance_social_start_form.xml
./view/recibo_form.xml
./view/recibo_tree.xml
./view/sanction_form.xml
./view/sanction_tree.xml
./view/vacation_form.xml
./view/vacation_tree.xml
trytonar_cooperative_ar.egg-info/PKG-INFO
trytonar_cooperative_ar.egg-info/SOURCES.txt
trytonar_cooperative_ar.egg-info/dependency_links.txt
trytonar_cooperative_ar.egg-info/entry_points.txt
trytonar_cooperative_ar.egg-info/not-zip-safe
trytonar_cooperative_ar.egg-info/requires.txt
trytonar_cooperative_ar.egg-info/top_level.txt